examples/basic/__init__.py
examples/basic/__main__.py
examples/basic/tests.py
examples/fullasync/__init__.py
examples/fullasync/__main__.py
examples/fullasync/tests.py
examples/html/__init__.py
examples/html/__main__.py
examples/html/tests.py
examples/streamresponse/__init__.py
examples/streamresponse/__main__.py
examples/streamresponse/tests.py
examples/websocket/__init__.py
examples/websocket/__main__.py
roll/__init__.py
roll/extensions.py
roll/http.py
roll/io.py
roll/testing.py
roll/websocket.py
roll/worker.py
roll-0.13.3.dist-info/METADATA
roll-0.13.3.dist-info/WHEEL
roll-0.13.3.dist-info/entry_points.txt
roll-0.13.3.dist-info/top_level.txt
roll-0.13.3.dist-info/RECORD
